fuzzyjoin/__init__.py
fuzzyjoin/cli.py
fuzzyjoin/collate.py
fuzzyjoin/compare.py
fuzzyjoin/io.py
fuzzyjoin/utils.py
fuzzyjoin-0.5.2.dist-info/LICENSE
fuzzyjoin-0.5.2.dist-info/METADATA
fuzzyjoin-0.5.2.dist-info/WHEEL
fuzzyjoin-0.5.2.dist-info/entry_points.txt
fuzzyjoin-0.5.2.dist-info/top_level.txt
fuzzyjoin-0.5.2.dist-info/RECORD
